pairinteraction/cli.py
pairinteraction/complex.py
pairinteraction/custom_logging.py
pairinteraction/diagonalization.py
pairinteraction/duckdb.dll
pairinteraction/enums.py
pairinteraction/picomplex.py
pairinteraction/pireal.py
pairinteraction/py.typed
pairinteraction/real.py
pairinteraction/tbb12.dll
pairinteraction/units.py
pairinteraction/_backend.cp311-win_amd64.pyd
pairinteraction/_backend.pyi
pairinteraction/_info.cp311-win_amd64.pyd
pairinteraction/_info.pyi
pairinteraction/__init__.py
pairinteraction/__main__.py
pairinteraction/basis/basis_atom.py
pairinteraction/basis/basis_base.py
pairinteraction/basis/basis_pair.py
pairinteraction/basis/__init__.py
pairinteraction/database/database.py
pairinteraction/database/database.sql
pairinteraction/database/__init__.py
pairinteraction/ket/ket_atom.py
pairinteraction/ket/ket_base.py
pairinteraction/ket/ket_pair.py
pairinteraction/ket/__init__.py
pairinteraction/perturbative/c3.py
pairinteraction/perturbative/c6.py
pairinteraction/perturbative/effective_system_pair.py
pairinteraction/perturbative/perturbation_theory.py
pairinteraction/perturbative/perturbative.py
pairinteraction/perturbative/__init__.py
pairinteraction/state/state_atom.py
pairinteraction/state/state_base.py
pairinteraction/state/state_pair.py
pairinteraction/state/__init__.py
pairinteraction/system/green_tensor.py
pairinteraction/system/system_atom.py
pairinteraction/system/system_base.py
pairinteraction/system/system_pair.py
pairinteraction/system/__init__.py
pairinteraction/visualization/colormaps.py
pairinteraction/visualization/__init__.py
pairinteraction-2.3.1.dist-info/DELVEWHEEL
pairinteraction-2.3.1.dist-info/entry_points.txt
pairinteraction-2.3.1.dist-info/METADATA
pairinteraction-2.3.1.dist-info/RECORD
pairinteraction-2.3.1.dist-info/WHEEL
pairinteraction-2.3.1.dist-info/licenses/LICENSE.txt
pairinteraction-2.3.1.dist-info/licenses/LICENSES/LGPL-3.0-or-later.txt
pairinteraction-2.3.1.dist-info/licenses/LICENSES/MIT.txt
pairinteraction-2.3.1.dist-info/licenses/LICENSES-THIRD-PARTY/LICENSE-CPPTRACE.txt
pairinteraction-2.3.1.dist-info/licenses/LICENSES-THIRD-PARTY/LICENSE-DOCTEST.txt
pairinteraction-2.3.1.dist-info/licenses/LICENSES-THIRD-PARTY/LICENSE-DUCKDB.txt
pairinteraction-2.3.1.dist-info/licenses/LICENSES-THIRD-PARTY/LICENSE-EIGEN.txt
pairinteraction-2.3.1.dist-info/licenses/LICENSES-THIRD-PARTY/LICENSE-FMT.txt
pairinteraction-2.3.1.dist-info/licenses/LICENSES-THIRD-PARTY/LICENSE-LAPACK.txt
pairinteraction-2.3.1.dist-info/licenses/LICENSES-THIRD-PARTY/LICENSE-MINIZ.txt
pairinteraction-2.3.1.dist-info/licenses/LICENSES-THIRD-PARTY/LICENSE-NANOBIND.txt
pairinteraction-2.3.1.dist-info/licenses/LICENSES-THIRD-PARTY/LICENSE-NLOHMANN-JSON.txt
pairinteraction-2.3.1.dist-info/licenses/LICENSES-THIRD-PARTY/LICENSE-OPENSSL.txt
pairinteraction-2.3.1.dist-info/licenses/LICENSES-THIRD-PARTY/LICENSE-SPDLOG.txt
pairinteraction-2.3.1.dist-info/licenses/LICENSES-THIRD-PARTY/LICENSE-TBB.txt
pairinteraction.libs/cpptrace-a3162ecef422bcb08b243de286773215.dll
pairinteraction.libs/fmt-999a6d9dbeb7204f872541fbae7fb3bb.dll
pairinteraction.libs/icudt78-e059add25f77bf3b0953445c42b6c303.dll
pairinteraction.libs/icuin78.dll
pairinteraction.libs/icuuc78.dll
pairinteraction.libs/libcrypto-3-x64-9325e8486c61b3227abeacf635279a10.dll
pairinteraction.libs/libssl-3-x64-8868cdf228861053e5fde584ea9f2db0.dll
