Metadata-Version: 2.4
Name: pairinteraction
Version: 2.3.1
Summary: A Rydberg Interaction Calculator
Keywords: rydberg,atom interactions,pair potentials,mqdt,quantum physics
Author: PairInteraction Developers
Maintainer-Email: Sebastian Weber <seweber@posteo.de>, =?utf-8?q?Johannes_M=C3=B6gerle?= <johannes.moegerle@itp3.uni-stuttgart.de>
License-Expression: LGPL-3.0-or-later
License-File: LICENSE.txt
License-File: LICENSES/LGPL-3.0-or-later.txt
License-File: LICENSES/MIT.txt
License-File: LICENSES-THIRD-PARTY/LICENSE-CPPTRACE.txt
License-File: LICENSES-THIRD-PARTY/LICENSE-DOCTEST.txt
License-File: LICENSES-THIRD-PARTY/LICENSE-DUCKDB.txt
License-File: LICENSES-THIRD-PARTY/LICENSE-EIGEN.txt
License-File: LICENSES-THIRD-PARTY/LICENSE-FMT.txt
License-File: LICENSES-THIRD-PARTY/LICENSE-LAPACK.txt
License-File: LICENSES-THIRD-PARTY/LICENSE-MINIZ.txt
License-File: LICENSES-THIRD-PARTY/LICENSE-NANOBIND.txt
License-File: LICENSES-THIRD-PARTY/LICENSE-NLOHMANN-JSON.txt
License-File: LICENSES-THIRD-PARTY/LICENSE-OPENSSL.txt
License-File: LICENSES-THIRD-PARTY/LICENSE-SPDLOG.txt
License-File: LICENSES-THIRD-PARTY/LICENSE-TBB.txt
Classifier: Intended Audience :: Science/Research
Classifier: Operating System :: MacOS
Classifier: Operating System :: Microsoft :: Windows
Classifier: Operating System :: POSIX :: Linux
Classifier: Programming Language :: C++
Classifier: Programming Language :: Python
Classifier: Programming Language :: Python :: 3
Classifier: Programming Language :: Python :: 3 :: Only
Classifier: Programming Language :: Python :: 3.9
Classifier: Programming Language :: Python :: 3.10
Classifier: Programming Language :: Python :: 3.11
Classifier: Programming Language :: Python :: 3.12
Classifier: Programming Language :: Python :: 3.13
Classifier: Programming Language :: Python :: Implementation :: CPython
Classifier: Topic :: Scientific/Engineering
Classifier: Topic :: Scientific/Engineering :: Physics
Classifier: Typing :: Typed
Project-URL: Homepage, https://www.pairinteraction.org
Project-URL: Repository, https://github.com/pairinteraction/pairinteraction
Requires-Python: >=3.9
Requires-Dist: typing_extensions>=4.7
Requires-Dist: numpy>=2.0.2
Requires-Dist: scipy>=1.10
Requires-Dist: pint<0.25.1,>=0.24.4
Requires-Dist: colorama>=0.4.6
Requires-Dist: pyside6>=6.8.2
Requires-Dist: matplotlib>=3.8
Requires-Dist: mplcursors>=0.6
Requires-Dist: attrs>=24.0
Requires-Dist: nbconvert>=7.8
Requires-Dist: nbformat>=5.10
Requires-Dist: scipy-stubs>=1.15; python_version >= "3.10"
Requires-Dist: mkl==2025.3.0; sys_platform != "darwin"
